cogitator/__init__.py
cogitator/clustering.py
cogitator/embedding.py
cogitator/model/__init__.py
cogitator/model/base.py
cogitator/model/ollama.py
cogitator/model/openai.py
cogitator/model/openrouter.py
cogitator/py.typed
cogitator/schemas.py
cogitator/strategies/__init__.py
cogitator/strategies/auto_cot.py
cogitator/strategies/cdw_cot.py
cogitator/strategies/graph_of_thoughts.py
cogitator/strategies/least_to_most.py
cogitator/strategies/sc_cot.py
cogitator/strategies/tree_of_thoughts.py
cogitator/utils.py
cogitator-0.2.0.dist-info/METADATA
cogitator-0.2.0.dist-info/WHEEL
cogitator-0.2.0.dist-info/licenses/LICENSE
cogitator-0.2.0.dist-info/RECORD
