Metadata-Version: 2.4
Name: cogitator
Version: 0.2.0
Summary: A Python toolkit for chain-of-thought prompting
License: MIT
License-File: LICENSE
Keywords: prompt engineering,chain-of-thought,artificial intelligence,machine learning
Author: Hassan Abedi
Author-email: hassan.abedi.t+cogitator@gmail.com
Requires-Python: >=3.10,<4.0
Classifier: Development Status :: 4 - Beta
Classifier: Intended Audience :: Developers
Classifier: Intended Audience :: Science/Research
Classifier: License :: OSI Approved :: MIT License
Classifier: Programming Language :: Python :: 3
Classifier: Programming Language :: Python :: 3.10
Classifier: Programming Language :: Python :: 3.11
Classifier: Programming Language :: Python :: 3.12
Classifier: Programming Language :: Python :: 3.13
Classifier: Programming Language :: Python :: 3.14
Classifier: Topic :: Software Development :: Libraries
Classifier: Topic :: Software Development :: Libraries :: Python Modules
Classifier: Topic :: Scientific/Engineering
Classifier: Topic :: Scientific/Engineering :: Artificial Intelligence
Provides-Extra: dev
Requires-Dist: datasets (>=3.5.1,<4.0.0) ; extra == "dev"
Requires-Dist: griffe (>=1.7.3,<2.0.0) ; extra == "dev"
Requires-Dist: mkdocs (>=1.6.1,<2.0.0) ; extra == "dev"
Requires-Dist: mkdocs-material (>=9.6.12,<10.0.0) ; extra == "dev"
Requires-Dist: mkdocstrings-python (>=1.16.10,<2.0.0) ; extra == "dev"
Requires-Dist: mypy (>=1.11.1,<2.0.0) ; extra == "dev"
Requires-Dist: ollama (>=0.4.8,<1.0.0)
Requires-Dist: openai (>=1.76.2,<2.0.0)
Requires-Dist: polars (>=1.28.1,<2.0.0) ; extra == "dev"
Requires-Dist: pre-commit (>=4.2.0,<5.0.0) ; extra == "dev"
Requires-Dist: pydantic (>=2.11.4,<3.0.0)
Requires-Dist: pytest (>=8.0.1,<9.0.0) ; extra == "dev"
Requires-Dist: pytest-asyncio (>=0.26.0,<1.0.0) ; extra == "dev"
Requires-Dist: pytest-cov (>=6.0.0,<7.0.0) ; extra == "dev"
Requires-Dist: pytest-mock (>=3.14.0,<4.0.0) ; extra == "dev"
Requires-Dist: pyyaml (>=6.0.2,<7.0.0) ; extra == "dev"
Requires-Dist: ruff (>=0.11.7,<1.0.0) ; extra == "dev"
Requires-Dist: scikit-learn (>=1.6.1,<2.0.0)
Requires-Dist: sentence-transformers (>=5.1.0,<6.0.0)
Requires-Dist: tiktoken (>=0.9.0,<1.0.0)
Project-URL: Documentation, https://habedi.github.io/cogitator
Project-URL: Repository, https://github.com/habedi/cogitator
